MANIFEST.in
README.txt
setup.py
mlmetrics/__init__.py
mlmetrics/mlmetrics.py
multilabel_metrics.egg-info/PKG-INFO
multilabel_metrics.egg-info/SOURCES.txt
multilabel_metrics.egg-info/dependency_links.txt
multilabel_metrics.egg-info/top_level.txt