Metadata-Version: 1.1
Name: multilabel-metrics
Version: 0.0.1
Summary: Multilabel classification metrics for Python
Home-page: https://github.com/hell-sing/multi-label-metrics
Author: Abhishek Verma
Author-email: abhishek_verma@hotmail.com
License: GNU_GPL licence, see LICENCE.txt
Keywords: classification metrics machine-learning
Platform: UNKNOWN
Classifier: Development Status :: 3 - Alpha
Classifier: Intended Audience :: Developers
Classifier: Topic :: Software Development :: Build Tools
Classifier: Programming Language :: Python :: 3
Classifier: Programming Language :: Python :: 3.3
Classifier: Programming Language :: Python :: 3.4
Classifier: Programming Language :: Python :: 3.5
